adguardhome_logsync/__init__.py
adguardhome_logsync/__main__.py
adguardhome_logsync/main.py
adguardhome_logsync/utils/__init__.py
adguardhome_logsync/utils/querylog_copy.py
adguardhome_logsync/utils/querylog_merge.py
adguardhome_logsync-0.1.3.dist-info/licenses/LICENSE
adguardhome_logsync-0.1.3.dist-info/METADATA
adguardhome_logsync-0.1.3.dist-info/WHEEL
adguardhome_logsync-0.1.3.dist-info/entry_points.txt
adguardhome_logsync-0.1.3.dist-info/top_level.txt
adguardhome_logsync-0.1.3.dist-info/RECORD
