Metadata-Version: 2.4
Name: adguardhome-logsync
Version: 0.1.3
Summary: A Python tool to synchronize AdGuard Home query logs between multiple instances
Author-email: xz-dev <xiangzhedev@gmail.com>
License-Expression: BSD-3-Clause
Project-URL: Homepage, https://github.com/xz-dev/AdGuardHome-LogSync
Project-URL: Repository, https://github.com/xz-dev/AdGuardHome-LogSync
Project-URL: Issues, https://github.com/xz-dev/AdGuardHome-LogSync/issues
Keywords: adguard,dns,log,sync
Classifier: Development Status :: 3 - Alpha
Classifier: Intended Audience :: System Administrators
Classifier: Operating System :: OS Independent
Classifier: Programming Language :: Python :: 3
Classifier: Programming Language :: Python :: 3.9
Classifier: Programming Language :: Python :: 3.10
Classifier: Programming Language :: Python :: 3.11
Classifier: Programming Language :: Python :: 3.12
Classifier: Programming Language :: Python :: 3.13
Classifier: Topic :: System :: Networking :: Monitoring
Classifier: Topic :: System :: Systems Administration
Requires-Python: >=3.9
License-File: LICENSE
Requires-Dist: sortedcontainers==2.4.0
Requires-Dist: orjson==3.10.18
Requires-Dist: aiofiles==24.1.0
Dynamic: license-file
